{
  "timestamp": "2025-12-11T23:41:38.820190",
  "graph_summary": {
    "nodes": 32,
    "edges": 90,
    "density": 0.0907258064516129,
    "is_connected": true,
    "connected_components": 1,
    "node_types": {
      "Node": 5,
      "Broker": 2,
      "Application": 15,
      "Topic": 10
    },
    "edge_types": {
      "RUNS_ON": 17,
      "ROUTES": 10,
      "PUBLISHES_TO": 10,
      "SUBSCRIBES_TO": 22,
      "DEPENDS_ON": 31
    },
    "degree_stats": {
      "avg": 5.62,
      "max": 19,
      "min": 1
    },
    "articulation_points": {
      "count": 2,
      "nodes": [
        "app_14",
        "broker_0"
      ]
    },
    "bridges": {
      "count": 2,
      "edges": [
        [
          "cloud_4",
          "app_14"
        ],
        [
          "broker_0",
          "topic_0"
        ]
      ]
    },
    "avg_clustering": 0.2521,
    "diameter": 5
  },
  "criticality_analysis": {
    "scores": {
      "edge_0": {
        "component": "edge_0",
        "type": "Node",
        "composite_score": 0.0187,
        "level": "MINIMAL",
        "betweenness_norm": 0.0,
        "is_articulation_point": false,
        "impact_score": 0.0625,
        "degree_centrality": 0.0968,
        "closeness_centrality": 0.1403,
        "pagerank": 0.047,
        "components_affected": 11,
        "reachability_loss_pct": 6.25
      },
      "edge_1": {
        "component": "edge_1",
        "type": "Node",
        "composite_score": 0.0206,
        "level": "MINIMAL",
        "betweenness_norm": 0.0,
        "is_articulation_point": false,
        "impact_score": 0.0688,
        "degree_centrality": 0.1613,
        "closeness_centrality": 0.2296,
        "pagerank": 0.0738,
        "components_affected": 12,
        "reachability_loss_pct": 6.88
      },
      "compute_2": {
        "component": "compute_2",
        "type": "Node",
        "composite_score": 0.0056,
        "level": "MINIMAL",
        "betweenness_norm": 0.0,
        "is_articulation_point": false,
        "impact_score": 0.0187,
        "degree_centrality": 0.0968,
        "closeness_centrality": 0.0968,
        "pagerank": 0.0361,
        "components_affected": 4,
        "reachability_loss_pct": 1.88
      },
      "compute_3": {
        "component": "compute_3",
        "type": "Node",
        "composite_score": 0.015,
        "level": "MINIMAL",
        "betweenness_norm": 0.0,
        "is_articulation_point": false,
        "impact_score": 0.05,
        "degree_centrality": 0.1613,
        "closeness_centrality": 0.1588,
        "pagerank": 0.033,
        "components_affected": 9,
        "reachability_loss_pct": 5.0
      },
      "cloud_4": {
        "component": "cloud_4",
        "type": "Node",
        "composite_score": 0.0112,
        "level": "MINIMAL",
        "betweenness_norm": 0.0,
        "is_articulation_point": false,
        "impact_score": 0.0375,
        "degree_centrality": 0.0323,
        "closeness_centrality": 0.0829,
        "pagerank": 0.0245,
        "components_affected": 7,
        "reachability_loss_pct": 3.75
      },
      "broker_0": {
        "component": "broker_0",
        "type": "Broker",
        "composite_score": 0.3112,
        "level": "LOW",
        "betweenness_norm": 0.0,
        "is_articulation_point": true,
        "impact_score": 0.0375,
        "degree_centrality": 0.1935,
        "closeness_centrality": 0.0,
        "pagerank": 0.0203,
        "components_affected": 7,
        "reachability_loss_pct": 3.75
      },
      "broker_1": {
        "component": "broker_1",
        "type": "Broker",
        "composite_score": 0.0112,
        "level": "MINIMAL",
        "betweenness_norm": 0.0,
        "is_articulation_point": false,
        "impact_score": 0.0375,
        "degree_centrality": 0.1935,
        "closeness_centrality": 0.0,
        "pagerank": 0.0203,
        "components_affected": 7,
        "reachability_loss_pct": 3.75
      },
      "app_0": {
        "component": "app_0",
        "type": "Application",
        "composite_score": 0.02,
        "level": "MINIMAL",
        "betweenness_norm": 0.0125,
        "is_articulation_point": false,
        "impact_score": 0.05,
        "degree_centrality": 0.1613,
        "closeness_centrality": 0.1056,
        "pagerank": 0.0244,
        "components_affected": 9,
        "reachability_loss_pct": 5.0
      },
      "app_1": {
        "component": "app_1",
        "type": "Application",
        "composite_score": 0.0304,
        "level": "MINIMAL",
        "betweenness_norm": 0.0385,
        "is_articulation_point": false,
        "impact_score": 0.05,
        "degree_centrality": 0.129,
        "closeness_centrality": 0.0968,
        "pagerank": 0.0228,
        "components_affected": 9,
        "reachability_loss_pct": 5.0
      },
      "app_2": {
        "component": "app_2",
        "type": "Application",
        "composite_score": 0.3753,
        "level": "LOW",
        "betweenness_norm": 0.6663,
        "is_articulation_point": false,
        "impact_score": 0.3625,
        "degree_centrality": 0.2903,
        "closeness_centrality": 0.1613,
        "pagerank": 0.0329,
        "components_affected": 24,
        "reachability_loss_pct": 36.25
      },
      "app_3": {
        "component": "app_3",
        "type": "Application",
        "composite_score": 0.0413,
        "level": "MINIMAL",
        "betweenness_norm": 0.0,
        "is_articulation_point": false,
        "impact_score": 0.1375,
        "degree_centrality": 0.129,
        "closeness_centrality": 0.0,
        "pagerank": 0.0203,
        "components_affected": 23,
        "reachability_loss_pct": 13.75
      },
      "app_4": {
        "component": "app_4",
        "type": "Application",
        "composite_score": 0.0418,
        "level": "MINIMAL",
        "betweenness_norm": 0.0577,
        "is_articulation_point": false,
        "impact_score": 0.0625,
        "degree_centrality": 0.1613,
        "closeness_centrality": 0.1216,
        "pagerank": 0.0286,
        "components_affected": 10,
        "reachability_loss_pct": 6.25
      },
      "app_5": {
        "component": "app_5",
        "type": "Application",
        "composite_score": 0.0075,
        "level": "MINIMAL",
        "betweenness_norm": 0.0,
        "is_articulation_point": false,
        "impact_score": 0.025,
        "degree_centrality": 0.0968,
        "closeness_centrality": 0.0,
        "pagerank": 0.0203,
        "components_affected": 5,
        "reachability_loss_pct": 2.5
      },
      "app_6": {
        "component": "app_6",
        "type": "Application",
        "composite_score": 0.0037,
        "level": "MINIMAL",
        "betweenness_norm": 0.0,
        "is_articulation_point": false,
        "impact_score": 0.0125,
        "degree_centrality": 0.0645,
        "closeness_centrality": 0.0,
        "pagerank": 0.0203,
        "components_affected": 3,
        "reachability_loss_pct": 1.25
      },
      "app_7": {
        "component": "app_7",
        "type": "Application",
        "composite_score": 0.0277,
        "level": "MINIMAL",
        "betweenness_norm": 0.0317,
        "is_articulation_point": false,
        "impact_score": 0.05,
        "degree_centrality": 0.2258,
        "closeness_centrality": 0.1659,
        "pagerank": 0.0329,
        "components_affected": 9,
        "reachability_loss_pct": 5.0
      },
      "app_8": {
        "component": "app_8",
        "type": "Application",
        "composite_score": 0.0413,
        "level": "MINIMAL",
        "betweenness_norm": 0.0,
        "is_articulation_point": false,
        "impact_score": 0.1375,
        "degree_centrality": 0.3548,
        "closeness_centrality": 0.0,
        "pagerank": 0.0203,
        "components_affected": 23,
        "reachability_loss_pct": 13.75
      },
      "app_9": {
        "component": "app_9",
        "type": "Application",
        "composite_score": 0.5444,
        "level": "MEDIUM",
        "betweenness_norm": 1.0,
        "is_articulation_point": false,
        "impact_score": 0.4813,
        "degree_centrality": 0.6129,
        "closeness_centrality": 0.1008,
        "pagerank": 0.0289,
        "components_affected": 24,
        "reachability_loss_pct": 48.12
      },
      "app_10": {
        "component": "app_10",
        "type": "Application",
        "composite_score": 0.02,
        "level": "MINIMAL",
        "betweenness_norm": 0.0125,
        "is_articulation_point": false,
        "impact_score": 0.05,
        "degree_centrality": 0.1613,
        "closeness_centrality": 0.1056,
        "pagerank": 0.0244,
        "components_affected": 9,
        "reachability_loss_pct": 5.0
      },
      "app_11": {
        "component": "app_11",
        "type": "Application",
        "composite_score": 0.0295,
        "level": "MINIMAL",
        "betweenness_norm": 0.0269,
        "is_articulation_point": false,
        "impact_score": 0.0625,
        "degree_centrality": 0.1613,
        "closeness_centrality": 0.1216,
        "pagerank": 0.0277,
        "components_affected": 10,
        "reachability_loss_pct": 6.25
      },
      "app_12": {
        "component": "app_12",
        "type": "Application",
        "composite_score": 0.0394,
        "level": "MINIMAL",
        "betweenness_norm": 0.0,
        "is_articulation_point": false,
        "impact_score": 0.1313,
        "degree_centrality": 0.5161,
        "closeness_centrality": 0.0,
        "pagerank": 0.0203,
        "components_affected": 22,
        "reachability_loss_pct": 13.12
      },
      "app_13": {
        "component": "app_13",
        "type": "Application",
        "composite_score": 0.036,
        "level": "MINIMAL",
        "betweenness_norm": 0.0385,
        "is_articulation_point": false,
        "impact_score": 0.0688,
        "degree_centrality": 0.1935,
        "closeness_centrality": 0.0968,
        "pagerank": 0.0228,
        "components_affected": 12,
        "reachability_loss_pct": 6.88
      },
      "app_14": {
        "component": "app_14",
        "type": "Application",
        "composite_score": 0.3947,
        "level": "LOW",
        "betweenness_norm": 0.0962,
        "is_articulation_point": true,
        "impact_score": 0.1875,
        "degree_centrality": 0.2581,
        "closeness_centrality": 0.1008,
        "pagerank": 0.0244,
        "components_affected": 24,
        "reachability_loss_pct": 18.75
      },
      "topic_0": {
        "component": "topic_0",
        "type": "Topic",
        "composite_score": 0.0019,
        "level": "MINIMAL",
        "betweenness_norm": 0.0,
        "is_articulation_point": false,
        "impact_score": 0.0063,
        "degree_centrality": 0.0323,
        "closeness_centrality": 0.0323,
        "pagerank": 0.0232,
        "components_affected": 2,
        "reachability_loss_pct": 0.62
      },
      "topic_1": {
        "component": "topic_1",
        "type": "Topic",
        "composite_score": 0.0037,
        "level": "MINIMAL",
        "betweenness_norm": 0.0,
        "is_articulation_point": false,
        "impact_score": 0.0125,
        "degree_centrality": 0.0645,
        "closeness_centrality": 0.0645,
        "pagerank": 0.0248,
        "components_affected": 3,
        "reachability_loss_pct": 1.25
      },
      "topic_2": {
        "component": "topic_2",
        "type": "Topic",
        "composite_score": 0.015,
        "level": "MINIMAL",
        "betweenness_norm": 0.0,
        "is_articulation_point": false,
        "impact_score": 0.05,
        "degree_centrality": 0.129,
        "closeness_centrality": 0.1475,
        "pagerank": 0.0354,
        "components_affected": 9,
        "reachability_loss_pct": 5.0
      },
      "topic_3": {
        "component": "topic_3",
        "type": "Topic",
        "composite_score": 0.0131,
        "level": "MINIMAL",
        "betweenness_norm": 0.0,
        "is_articulation_point": false,
        "impact_score": 0.0437,
        "degree_centrality": 0.129,
        "closeness_centrality": 0.1581,
        "pagerank": 0.0332,
        "components_affected": 8,
        "reachability_loss_pct": 4.38
      },
      "topic_4": {
        "component": "topic_4",
        "type": "Topic",
        "composite_score": 0.0037,
        "level": "MINIMAL",
        "betweenness_norm": 0.0,
        "is_articulation_point": false,
        "impact_score": 0.0125,
        "degree_centrality": 0.0645,
        "closeness_centrality": 0.0645,
        "pagerank": 0.0318,
        "components_affected": 3,
        "reachability_loss_pct": 1.25
      },
      "topic_5": {
        "component": "topic_5",
        "type": "Topic",
        "composite_score": 0.015,
        "level": "MINIMAL",
        "betweenness_norm": 0.0,
        "is_articulation_point": false,
        "impact_score": 0.05,
        "degree_centrality": 0.2581,
        "closeness_centrality": 0.2581,
        "pagerank": 0.0567,
        "components_affected": 9,
        "reachability_loss_pct": 5.0
      },
      "topic_6": {
        "component": "topic_6",
        "type": "Topic",
        "composite_score": 0.0169,
        "level": "MINIMAL",
        "betweenness_norm": 0.0,
        "is_articulation_point": false,
        "impact_score": 0.0563,
        "degree_centrality": 0.1613,
        "closeness_centrality": 0.1742,
        "pagerank": 0.0436,
        "components_affected": 10,
        "reachability_loss_pct": 5.62
      },
      "topic_7": {
        "component": "topic_7",
        "type": "Topic",
        "composite_score": 0.015,
        "level": "MINIMAL",
        "betweenness_norm": 0.0,
        "is_articulation_point": false,
        "impact_score": 0.05,
        "degree_centrality": 0.129,
        "closeness_centrality": 0.1475,
        "pagerank": 0.0306,
        "components_affected": 9,
        "reachability_loss_pct": 5.0
      },
      "topic_8": {
        "component": "topic_8",
        "type": "Topic",
        "composite_score": 0.0169,
        "level": "MINIMAL",
        "betweenness_norm": 0.0,
        "is_articulation_point": false,
        "impact_score": 0.0563,
        "degree_centrality": 0.2258,
        "closeness_centrality": 0.2177,
        "pagerank": 0.0522,
        "components_affected": 10,
        "reachability_loss_pct": 5.62
      },
      "topic_9": {
        "component": "topic_9",
        "type": "Topic",
        "composite_score": 0.0169,
        "level": "MINIMAL",
        "betweenness_norm": 0.0,
        "is_articulation_point": false,
        "impact_score": 0.0563,
        "degree_centrality": 0.1613,
        "closeness_centrality": 0.1742,
        "pagerank": 0.0423,
        "components_affected": 10,
        "reachability_loss_pct": 5.62
      }
    },
    "summary": {
      "total_components": 32,
      "avg_score": 0.0677,
      "max_score": 0.5444,
      "critical_count": 0,
      "high_count": 0,
      "medium_count": 1,
      "low_count": 3,
      "minimal_count": 28,
      "articulation_points": 2
    }
  },
  "structural_analysis": {
    "nodes": 32,
    "edges": 90,
    "density": 0.0907258064516129,
    "is_connected": true,
    "connected_components": 1,
    "node_types": {
      "Node": 5,
      "Broker": 2,
      "Application": 15,
      "Topic": 10
    },
    "edge_types": {
      "RUNS_ON": 17,
      "ROUTES": 10,
      "PUBLISHES_TO": 10,
      "SUBSCRIBES_TO": 22,
      "DEPENDS_ON": 31
    },
    "degree_stats": {
      "avg": 5.62,
      "max": 19,
      "min": 1
    },
    "articulation_points": {
      "count": 2,
      "nodes": [
        "app_14",
        "broker_0"
      ]
    },
    "bridges": {
      "count": 2,
      "edges": [
        [
          "cloud_4",
          "app_14"
        ],
        [
          "broker_0",
          "topic_0"
        ]
      ]
    },
    "avg_clustering": 0.2521,
    "diameter": 5
  },
  "antipatterns": [],
  "simulation_results": {},
  "recommendations": [
    {
      "priority": "HIGH",
      "category": "Network Topology",
      "component": "Network",
      "issue": "2 bridge edges detected",
      "recommendation": "Add redundant network paths",
      "risk_reduction": "High"
    }
  ],
  "execution_time": {
    "load_graph": 0.0008208751678466797,
    "structural_analysis": 0.005663633346557617,
    "criticality_scoring": 0.2659180164337158
  }
}