{
  "simulations": [
    {
      "simulation_id": "sim_1",
      "simulation_type": "single_failure",
      "start_time": "2025-12-11T23:41:39.120556",
      "end_time": "2025-12-11T23:41:39.120848",
      "duration_ms": 0.292,
      "failed_components": [
        "app_0"
      ],
      "cascade_failures": [],
      "affected_components": [
        "app_9",
        "edge_1",
        "app_12",
        "app_8",
        "topic_8"
      ],
      "isolated_components": [],
      "failure_events": [
        {
          "component": "app_0",
          "failure_type": "complete",
          "failure_mode": "crash",
          "timestamp": "2025-12-11T23:41:39.120556",
          "severity": 1.0,
          "cause": "Primary failure (simulated)",
          "is_cascade": false,
          "cascade_depth": 0,
          "recovery_time_ms": null
        }
      ],
      "impact_metrics": {
        "impact_score": 0.1875,
        "resilience_score": 0.8125,
        "service_continuity": 0.9688
      },
      "path_analysis": {
        "original_paths": 90,
        "affected_paths": 5,
        "remaining_paths": 85
      },
      "reachability": {
        "original": 160,
        "lost": 8,
        "loss_percentage": 5.0
      },
      "connectivity": {
        "original_components": 1,
        "resulting_components": 1,
        "fragmentation": 0
      },
      "statistics": {
        "total_nodes": 32,
        "total_edges": 90,
        "failed_count": 1,
        "cascade_count": 0,
        "affected_count": 5,
        "isolated_count": 0,
        "primary_failures": 1,
        "by_type": {
          "Application": 1
        }
      }
    },
    {
      "simulation_id": "sim_2",
      "simulation_type": "single_failure",
      "start_time": "2025-12-11T23:41:39.124150",
      "end_time": "2025-12-11T23:41:39.124445",
      "duration_ms": 0.29500000000000004,
      "failed_components": [
        "app_1"
      ],
      "cascade_failures": [],
      "affected_components": [
        "app_9",
        "app_12",
        "topic_2",
        "edge_0"
      ],
      "isolated_components": [],
      "failure_events": [
        {
          "component": "app_1",
          "failure_type": "complete",
          "failure_mode": "crash",
          "timestamp": "2025-12-11T23:41:39.124150",
          "severity": 1.0,
          "cause": "Primary failure (simulated)",
          "is_cascade": false,
          "cascade_depth": 0,
          "recovery_time_ms": null
        }
      ],
      "impact_metrics": {
        "impact_score": 0.1562,
        "resilience_score": 0.8438,
        "service_continuity": 0.9688
      },
      "path_analysis": {
        "original_paths": 90,
        "affected_paths": 4,
        "remaining_paths": 86
      },
      "reachability": {
        "original": 160,
        "lost": 8,
        "loss_percentage": 5.0
      },
      "connectivity": {
        "original_components": 1,
        "resulting_components": 1,
        "fragmentation": 0
      },
      "statistics": {
        "total_nodes": 32,
        "total_edges": 90,
        "failed_count": 1,
        "cascade_count": 0,
        "affected_count": 4,
        "isolated_count": 0,
        "primary_failures": 1,
        "by_type": {
          "Application": 1
        }
      }
    },
    {
      "simulation_id": "sim_3",
      "simulation_type": "single_failure",
      "start_time": "2025-12-11T23:41:39.125490",
      "end_time": "2025-12-11T23:41:39.125739",
      "duration_ms": 0.24899999999999997,
      "failed_components": [
        "app_2"
      ],
      "cascade_failures": [],
      "affected_components": [
        "topic_3",
        "app_9",
        "edge_1",
        "app_12",
        "app_8",
        "app_3",
        "app_14",
        "topic_5"
      ],
      "isolated_components": [],
      "failure_events": [
        {
          "component": "app_2",
          "failure_type": "complete",
          "failure_mode": "crash",
          "timestamp": "2025-12-11T23:41:39.125490",
          "severity": 1.0,
          "cause": "Primary failure (simulated)",
          "is_cascade": false,
          "cascade_depth": 0,
          "recovery_time_ms": null
        }
      ],
      "impact_metrics": {
        "impact_score": 0.2812,
        "resilience_score": 0.7188,
        "service_continuity": 0.9688
      },
      "path_analysis": {
        "original_paths": 90,
        "affected_paths": 9,
        "remaining_paths": 81
      },
      "reachability": {
        "original": 160,
        "lost": 58,
        "loss_percentage": 36.25
      },
      "connectivity": {
        "original_components": 1,
        "resulting_components": 1,
        "fragmentation": 0
      },
      "statistics": {
        "total_nodes": 32,
        "total_edges": 90,
        "failed_count": 1,
        "cascade_count": 0,
        "affected_count": 8,
        "isolated_count": 0,
        "primary_failures": 1,
        "by_type": {
          "Application": 1
        }
      }
    },
    {
      "simulation_id": "sim_4",
      "simulation_type": "single_failure",
      "start_time": "2025-12-11T23:41:39.126673",
      "end_time": "2025-12-11T23:41:39.126913",
      "duration_ms": 0.24000000000000002,
      "failed_components": [
        "app_3"
      ],
      "cascade_failures": [],
      "affected_components": [
        "topic_5",
        "compute_2",
        "app_2",
        "app_7"
      ],
      "isolated_components": [],
      "failure_events": [
        {
          "component": "app_3",
          "failure_type": "complete",
          "failure_mode": "crash",
          "timestamp": "2025-12-11T23:41:39.126673",
          "severity": 1.0,
          "cause": "Primary failure (simulated)",
          "is_cascade": false,
          "cascade_depth": 0,
          "recovery_time_ms": null
        }
      ],
      "impact_metrics": {
        "impact_score": 0.1562,
        "resilience_score": 0.8438,
        "service_continuity": 0.9688
      },
      "path_analysis": {
        "original_paths": 90,
        "affected_paths": 4,
        "remaining_paths": 86
      },
      "reachability": {
        "original": 160,
        "lost": 22,
        "loss_percentage": 13.75
      },
      "connectivity": {
        "original_components": 1,
        "resulting_components": 1,
        "fragmentation": 0
      },
      "statistics": {
        "total_nodes": 32,
        "total_edges": 90,
        "failed_count": 1,
        "cascade_count": 0,
        "affected_count": 4,
        "isolated_count": 0,
        "primary_failures": 1,
        "by_type": {
          "Application": 1
        }
      }
    },
    {
      "simulation_id": "sim_5",
      "simulation_type": "single_failure",
      "start_time": "2025-12-11T23:41:39.127864",
      "end_time": "2025-12-11T23:41:39.128168",
      "duration_ms": 0.304,
      "failed_components": [
        "app_4"
      ],
      "cascade_failures": [],
      "affected_components": [
        "app_9",
        "topic_6",
        "app_12",
        "app_5",
        "edge_0"
      ],
      "isolated_components": [],
      "failure_events": [
        {
          "component": "app_4",
          "failure_type": "complete",
          "failure_mode": "crash",
          "timestamp": "2025-12-11T23:41:39.127864",
          "severity": 1.0,
          "cause": "Primary failure (simulated)",
          "is_cascade": false,
          "cascade_depth": 0,
          "recovery_time_ms": null
        }
      ],
      "impact_metrics": {
        "impact_score": 0.1875,
        "resilience_score": 0.8125,
        "service_continuity": 0.9688
      },
      "path_analysis": {
        "original_paths": 90,
        "affected_paths": 5,
        "remaining_paths": 85
      },
      "reachability": {
        "original": 160,
        "lost": 10,
        "loss_percentage": 6.25
      },
      "connectivity": {
        "original_components": 1,
        "resulting_components": 1,
        "fragmentation": 0
      },
      "statistics": {
        "total_nodes": 32,
        "total_edges": 90,
        "failed_count": 1,
        "cascade_count": 0,
        "affected_count": 5,
        "isolated_count": 0,
        "primary_failures": 1,
        "by_type": {
          "Application": 1
        }
      }
    },
    {
      "simulation_id": "sim_6",
      "simulation_type": "single_failure",
      "start_time": "2025-12-11T23:41:39.129163",
      "end_time": "2025-12-11T23:41:39.129386",
      "duration_ms": 0.223,
      "failed_components": [
        "app_5"
      ],
      "cascade_failures": [],
      "affected_components": [
        "app_4",
        "compute_3",
        "topic_6"
      ],
      "isolated_components": [],
      "failure_events": [
        {
          "component": "app_5",
          "failure_type": "complete",
          "failure_mode": "crash",
          "timestamp": "2025-12-11T23:41:39.129163",
          "severity": 1.0,
          "cause": "Primary failure (simulated)",
          "is_cascade": false,
          "cascade_depth": 0,
          "recovery_time_ms": null
        }
      ],
      "impact_metrics": {
        "impact_score": 0.125,
        "resilience_score": 0.875,
        "service_continuity": 0.9688
      },
      "path_analysis": {
        "original_paths": 90,
        "affected_paths": 3,
        "remaining_paths": 87
      },
      "reachability": {
        "original": 160,
        "lost": 4,
        "loss_percentage": 2.5
      },
      "connectivity": {
        "original_components": 1,
        "resulting_components": 1,
        "fragmentation": 0
      },
      "statistics": {
        "total_nodes": 32,
        "total_edges": 90,
        "failed_count": 1,
        "cascade_count": 0,
        "affected_count": 3,
        "isolated_count": 0,
        "primary_failures": 1,
        "by_type": {
          "Application": 1
        }
      }
    },
    {
      "simulation_id": "sim_7",
      "simulation_type": "single_failure",
      "start_time": "2025-12-11T23:41:39.130351",
      "end_time": "2025-12-11T23:41:39.130573",
      "duration_ms": 0.222,
      "failed_components": [
        "app_6"
      ],
      "cascade_failures": [],
      "affected_components": [
        "compute_2",
        "topic_4"
      ],
      "isolated_components": [],
      "failure_events": [
        {
          "component": "app_6",
          "failure_type": "complete",
          "failure_mode": "crash",
          "timestamp": "2025-12-11T23:41:39.130351",
          "severity": 1.0,
          "cause": "Primary failure (simulated)",
          "is_cascade": false,
          "cascade_depth": 0,
          "recovery_time_ms": null
        }
      ],
      "impact_metrics": {
        "impact_score": 0.0938,
        "resilience_score": 0.9062,
        "service_continuity": 0.9688
      },
      "path_analysis": {
        "original_paths": 90,
        "affected_paths": 2,
        "remaining_paths": 88
      },
      "reachability": {
        "original": 160,
        "lost": 2,
        "loss_percentage": 1.25
      },
      "connectivity": {
        "original_components": 1,
        "resulting_components": 1,
        "fragmentation": 0
      },
      "statistics": {
        "total_nodes": 32,
        "total_edges": 90,
        "failed_count": 1,
        "cascade_count": 0,
        "affected_count": 2,
        "isolated_count": 0,
        "primary_failures": 1,
        "by_type": {
          "Application": 1
        }
      }
    },
    {
      "simulation_id": "sim_8",
      "simulation_type": "single_failure",
      "start_time": "2025-12-11T23:41:39.131501",
      "end_time": "2025-12-11T23:41:39.131817",
      "duration_ms": 0.316,
      "failed_components": [
        "app_7"
      ],
      "cascade_failures": [],
      "affected_components": [
        "app_9",
        "edge_1",
        "app_12",
        "app_8",
        "app_3",
        "app_14",
        "topic_5"
      ],
      "isolated_components": [],
      "failure_events": [
        {
          "component": "app_7",
          "failure_type": "complete",
          "failure_mode": "crash",
          "timestamp": "2025-12-11T23:41:39.131501",
          "severity": 1.0,
          "cause": "Primary failure (simulated)",
          "is_cascade": false,
          "cascade_depth": 0,
          "recovery_time_ms": null
        }
      ],
      "impact_metrics": {
        "impact_score": 0.25,
        "resilience_score": 0.75,
        "service_continuity": 0.9688
      },
      "path_analysis": {
        "original_paths": 90,
        "affected_paths": 7,
        "remaining_paths": 83
      },
      "reachability": {
        "original": 160,
        "lost": 8,
        "loss_percentage": 5.0
      },
      "connectivity": {
        "original_components": 1,
        "resulting_components": 1,
        "fragmentation": 0
      },
      "statistics": {
        "total_nodes": 32,
        "total_edges": 90,
        "failed_count": 1,
        "cascade_count": 0,
        "affected_count": 7,
        "isolated_count": 0,
        "primary_failures": 1,
        "by_type": {
          "Application": 1
        }
      }
    },
    {
      "simulation_id": "sim_9",
      "simulation_type": "single_failure",
      "start_time": "2025-12-11T23:41:39.132783",
      "end_time": "2025-12-11T23:41:39.133003",
      "duration_ms": 0.22,
      "failed_components": [
        "app_8"
      ],
      "cascade_failures": [],
      "affected_components": [
        "topic_3",
        "app_0",
        "app_9",
        "topic_5",
        "compute_3",
        "topic_1",
        "app_10",
        "app_14",
        "topic_8",
        "app_2",
        "app_7"
      ],
      "isolated_components": [],
      "failure_events": [
        {
          "component": "app_8",
          "failure_type": "complete",
          "failure_mode": "crash",
          "timestamp": "2025-12-11T23:41:39.132783",
          "severity": 1.0,
          "cause": "Primary failure (simulated)",
          "is_cascade": false,
          "cascade_depth": 0,
          "recovery_time_ms": null
        }
      ],
      "impact_metrics": {
        "impact_score": 0.375,
        "resilience_score": 0.625,
        "service_continuity": 0.9688
      },
      "path_analysis": {
        "original_paths": 90,
        "affected_paths": 11,
        "remaining_paths": 79
      },
      "reachability": {
        "original": 160,
        "lost": 22,
        "loss_percentage": 13.75
      },
      "connectivity": {
        "original_components": 1,
        "resulting_components": 1,
        "fragmentation": 0
      },
      "statistics": {
        "total_nodes": 32,
        "total_edges": 90,
        "failed_count": 1,
        "cascade_count": 0,
        "affected_count": 11,
        "isolated_count": 0,
        "primary_failures": 1,
        "by_type": {
          "Application": 1
        }
      }
    },
    {
      "simulation_id": "sim_10",
      "simulation_type": "single_failure",
      "start_time": "2025-12-11T23:41:39.133922",
      "end_time": "2025-12-11T23:41:39.134145",
      "duration_ms": 0.223,
      "failed_components": [
        "app_9"
      ],
      "cascade_failures": [],
      "affected_components": [
        "topic_3",
        "app_0",
        "topic_5",
        "app_1",
        "app_11",
        "topic_2",
        "app_4",
        "topic_6",
        "compute_3",
        "app_8",
        "app_13",
        "app_10",
        "app_14",
        "topic_9",
        "topic_8",
        "app_2",
        "topic_7",
        "app_7"
      ],
      "isolated_components": [],
      "failure_events": [
        {
          "component": "app_9",
          "failure_type": "complete",
          "failure_mode": "crash",
          "timestamp": "2025-12-11T23:41:39.133922",
          "severity": 1.0,
          "cause": "Primary failure (simulated)",
          "is_cascade": false,
          "cascade_depth": 0,
          "recovery_time_ms": null
        }
      ],
      "impact_metrics": {
        "impact_score": 0.5938,
        "resilience_score": 0.4062,
        "service_continuity": 0.9688
      },
      "path_analysis": {
        "original_paths": 90,
        "affected_paths": 19,
        "remaining_paths": 71
      },
      "reachability": {
        "original": 160,
        "lost": 77,
        "loss_percentage": 48.12
      },
      "connectivity": {
        "original_components": 1,
        "resulting_components": 1,
        "fragmentation": 0
      },
      "statistics": {
        "total_nodes": 32,
        "total_edges": 90,
        "failed_count": 1,
        "cascade_count": 0,
        "affected_count": 18,
        "isolated_count": 0,
        "primary_failures": 1,
        "by_type": {
          "Application": 1
        }
      }
    },
    {
      "simulation_id": "sim_11",
      "simulation_type": "single_failure",
      "start_time": "2025-12-11T23:41:39.134994",
      "end_time": "2025-12-11T23:41:39.135248",
      "duration_ms": 0.254,
      "failed_components": [
        "app_10"
      ],
      "cascade_failures": [],
      "affected_components": [
        "app_9",
        "edge_1",
        "app_12",
        "app_8",
        "topic_8"
      ],
      "isolated_components": [],
      "failure_events": [
        {
          "component": "app_10",
          "failure_type": "complete",
          "failure_mode": "crash",
          "timestamp": "2025-12-11T23:41:39.134994",
          "severity": 1.0,
          "cause": "Primary failure (simulated)",
          "is_cascade": false,
          "cascade_depth": 0,
          "recovery_time_ms": null
        }
      ],
      "impact_metrics": {
        "impact_score": 0.1875,
        "resilience_score": 0.8125,
        "service_continuity": 0.9688
      },
      "path_analysis": {
        "original_paths": 90,
        "affected_paths": 5,
        "remaining_paths": 85
      },
      "reachability": {
        "original": 160,
        "lost": 8,
        "loss_percentage": 5.0
      },
      "connectivity": {
        "original_components": 1,
        "resulting_components": 1,
        "fragmentation": 0
      },
      "statistics": {
        "total_nodes": 32,
        "total_edges": 90,
        "failed_count": 1,
        "cascade_count": 0,
        "affected_count": 5,
        "isolated_count": 0,
        "primary_failures": 1,
        "by_type": {
          "Application": 1
        }
      }
    },
    {
      "simulation_id": "sim_12",
      "simulation_type": "single_failure",
      "start_time": "2025-12-11T23:41:39.136410",
      "end_time": "2025-12-11T23:41:39.136730",
      "duration_ms": 0.32,
      "failed_components": [
        "app_11"
      ],
      "cascade_failures": [],
      "affected_components": [
        "app_9",
        "edge_1",
        "app_12",
        "app_13",
        "topic_9"
      ],
      "isolated_components": [],
      "failure_events": [
        {
          "component": "app_11",
          "failure_type": "complete",
          "failure_mode": "crash",
          "timestamp": "2025-12-11T23:41:39.136410",
          "severity": 1.0,
          "cause": "Primary failure (simulated)",
          "is_cascade": false,
          "cascade_depth": 0,
          "recovery_time_ms": null
        }
      ],
      "impact_metrics": {
        "impact_score": 0.1875,
        "resilience_score": 0.8125,
        "service_continuity": 0.9688
      },
      "path_analysis": {
        "original_paths": 90,
        "affected_paths": 5,
        "remaining_paths": 85
      },
      "reachability": {
        "original": 160,
        "lost": 10,
        "loss_percentage": 6.25
      },
      "connectivity": {
        "original_components": 1,
        "resulting_components": 1,
        "fragmentation": 0
      },
      "statistics": {
        "total_nodes": 32,
        "total_edges": 90,
        "failed_count": 1,
        "cascade_count": 0,
        "affected_count": 5,
        "isolated_count": 0,
        "primary_failures": 1,
        "by_type": {
          "Application": 1
        }
      }
    },
    {
      "simulation_id": "sim_13",
      "simulation_type": "single_failure",
      "start_time": "2025-12-11T23:41:39.137872",
      "end_time": "2025-12-11T23:41:39.138106",
      "duration_ms": 0.23399999999999999,
      "failed_components": [
        "app_12"
      ],
      "cascade_failures": [],
      "affected_components": [
        "topic_5",
        "app_0",
        "app_1",
        "app_11",
        "topic_2",
        "app_4",
        "topic_6",
        "compute_3",
        "app_13",
        "app_10",
        "app_14",
        "topic_9",
        "topic_8",
        "app_2",
        "topic_7",
        "app_7"
      ],
      "isolated_components": [],
      "failure_events": [
        {
          "component": "app_12",
          "failure_type": "complete",
          "failure_mode": "crash",
          "timestamp": "2025-12-11T23:41:39.137872",
          "severity": 1.0,
          "cause": "Primary failure (simulated)",
          "is_cascade": false,
          "cascade_depth": 0,
          "recovery_time_ms": null
        }
      ],
      "impact_metrics": {
        "impact_score": 0.5312,
        "resilience_score": 0.4688,
        "service_continuity": 0.9688
      },
      "path_analysis": {
        "original_paths": 90,
        "affected_paths": 16,
        "remaining_paths": 74
      },
      "reachability": {
        "original": 160,
        "lost": 21,
        "loss_percentage": 13.12
      },
      "connectivity": {
        "original_components": 1,
        "resulting_components": 1,
        "fragmentation": 0
      },
      "statistics": {
        "total_nodes": 32,
        "total_edges": 90,
        "failed_count": 1,
        "cascade_count": 0,
        "affected_count": 16,
        "isolated_count": 0,
        "primary_failures": 1,
        "by_type": {
          "Application": 1
        }
      }
    },
    {
      "simulation_id": "sim_14",
      "simulation_type": "single_failure",
      "start_time": "2025-12-11T23:41:39.139166",
      "end_time": "2025-12-11T23:41:39.139383",
      "duration_ms": 0.217,
      "failed_components": [
        "app_13"
      ],
      "cascade_failures": [],
      "affected_components": [
        "app_9",
        "app_11",
        "app_12",
        "topic_9",
        "topic_7",
        "edge_0"
      ],
      "isolated_components": [],
      "failure_events": [
        {
          "component": "app_13",
          "failure_type": "complete",
          "failure_mode": "crash",
          "timestamp": "2025-12-11T23:41:39.139166",
          "severity": 1.0,
          "cause": "Primary failure (simulated)",
          "is_cascade": false,
          "cascade_depth": 0,
          "recovery_time_ms": null
        }
      ],
      "impact_metrics": {
        "impact_score": 0.2188,
        "resilience_score": 0.7812,
        "service_continuity": 0.9688
      },
      "path_analysis": {
        "original_paths": 90,
        "affected_paths": 6,
        "remaining_paths": 84
      },
      "reachability": {
        "original": 160,
        "lost": 11,
        "loss_percentage": 6.88
      },
      "connectivity": {
        "original_components": 1,
        "resulting_components": 1,
        "fragmentation": 0
      },
      "statistics": {
        "total_nodes": 32,
        "total_edges": 90,
        "failed_count": 1,
        "cascade_count": 0,
        "affected_count": 6,
        "isolated_count": 0,
        "primary_failures": 1,
        "by_type": {
          "Application": 1
        }
      }
    },
    {
      "simulation_id": "sim_15",
      "simulation_type": "single_failure",
      "start_time": "2025-12-11T23:41:39.140494",
      "end_time": "2025-12-11T23:41:39.140741",
      "duration_ms": 0.247,
      "failed_components": [
        "app_14"
      ],
      "cascade_failures": [],
      "affected_components": [
        "topic_5",
        "app_9",
        "app_12",
        "app_8",
        "cloud_4",
        "topic_8",
        "app_2",
        "app_7"
      ],
      "isolated_components": [
        "cloud_4"
      ],
      "failure_events": [
        {
          "component": "app_14",
          "failure_type": "complete",
          "failure_mode": "crash",
          "timestamp": "2025-12-11T23:41:39.140494",
          "severity": 1.0,
          "cause": "Primary failure (simulated)",
          "is_cascade": false,
          "cascade_depth": 0,
          "recovery_time_ms": null
        }
      ],
      "impact_metrics": {
        "impact_score": 0.2812,
        "resilience_score": 0.7188,
        "service_continuity": 0.9688
      },
      "path_analysis": {
        "original_paths": 90,
        "affected_paths": 8,
        "remaining_paths": 82
      },
      "reachability": {
        "original": 160,
        "lost": 30,
        "loss_percentage": 18.75
      },
      "connectivity": {
        "original_components": 1,
        "resulting_components": 2,
        "fragmentation": 1
      },
      "statistics": {
        "total_nodes": 32,
        "total_edges": 90,
        "failed_count": 1,
        "cascade_count": 0,
        "affected_count": 8,
        "isolated_count": 1,
        "primary_failures": 1,
        "by_type": {
          "Application": 1
        }
      }
    }
  ],
  "count": 15,
  "exported_at": "2025-12-11T23:41:39.143842"
}